{
  "generated_at": "2026-05-03T11:56:32.244213",
  "environment": {
    "platform": "Windows-10-10.0.26200-SP0",
    "python": "3.10.20",
    "executable": "C:\\Users\\David Lochmann\\miniconda3\\envs\\pb-studio\\python.exe",
    "torch": "1.12.1+cu113",
    "torch.cuda": "11.3",
    "cuda_available": "True",
    "device_name": "NVIDIA GeForce GTX 1060",
    "device_capability": "(6, 1)",
    "total_vram_mb": 6143.9,
    "transformers": "4.38.2"
  },
  "results": [
    {
      "name": "baseline",
      "started_at": "2026-05-03T11:55:51.135523",
      "finished_at": "2026-05-03T11:55:57.549302",
      "status": "ok",
      "metadata": {},
      "error": "",
      "snapshots": [
        {
          "label": "baseline_before_torch_init",
          "timestamp": "2026-05-03T11:55:51.240282",
          "allocated_mb": 0.0,
          "reserved_mb": 0.0,
          "total_mb": 6143.9,
          "free_mb": 5217.0,
          "note": ""
        },
        {
          "label": "baseline_after_cuda_init",
          "timestamp": "2026-05-03T11:55:57.467380",
          "allocated_mb": 0.0,
          "reserved_mb": 2.0,
          "total_mb": 6143.9,
          "free_mb": 4907.0,
          "note": "1-tensor allocated"
        },
        {
          "label": "baseline_after_empty_cache",
          "timestamp": "2026-05-03T11:55:57.549302",
          "allocated_mb": 0.0,
          "reserved_mb": 0.0,
          "total_mb": 6143.9,
          "free_mb": 4909.0,
          "note": ""
        }
      ]
    },
    {
      "name": "clap",
      "started_at": "2026-05-03T11:55:57.552973",
      "finished_at": "2026-05-03T11:56:25.674756",
      "status": "ok",
      "metadata": {
        "model": "laion/larger_clap_music",
        "skip_inference": false,
        "feature_shape": [
          1,
          512
        ],
        "feature_dim": 512
      },
      "error": "",
      "snapshots": [
        {
          "label": "clap_before_load",
          "timestamp": "2026-05-03T11:55:57.552973",
          "allocated_mb": 0.0,
          "reserved_mb": 0.0,
          "total_mb": 6143.9,
          "free_mb": 4909.0,
          "note": ""
        },
        {
          "label": "clap_after_load",
          "timestamp": "2026-05-03T11:56:19.874657",
          "allocated_mb": 742.0,
          "reserved_mb": 776.0,
          "total_mb": 6143.9,
          "free_mb": 4133.0,
          "note": ""
        },
        {
          "label": "clap_after_processor",
          "timestamp": "2026-05-03T11:56:19.962904",
          "allocated_mb": 742.3,
          "reserved_mb": 778.0,
          "total_mb": 6143.9,
          "free_mb": 4131.0,
          "note": ""
        },
        {
          "label": "clap_after_inference",
          "timestamp": "2026-05-03T11:56:25.529639",
          "allocated_mb": 742.3,
          "reserved_mb": 808.0,
          "total_mb": 6143.9,
          "free_mb": 3865.0,
          "note": ""
        },
        {
          "label": "clap_after_unload_and_empty_cache",
          "timestamp": "2026-05-03T11:56:25.659107",
          "allocated_mb": 0.0,
          "reserved_mb": 0.0,
          "total_mb": 6143.9,
          "free_mb": 4673.0,
          "note": ""
        }
      ]
    },
    {
      "name": "siglip2",
      "started_at": "2026-05-03T11:56:25.674756",
      "finished_at": "2026-05-03T11:56:28.155394",
      "status": "error",
      "metadata": {
        "model": "google/siglip2-base-patch16-384",
        "batch_sizes_tried": [
          1,
          2,
          4,
          8
        ],
        "batch_results": {}
      },
      "error": "TypeError: expected str, bytes or os.PathLike object, not NoneType",
      "snapshots": [
        {
          "label": "siglip2_before_load",
          "timestamp": "2026-05-03T11:56:25.674756",
          "allocated_mb": 0.0,
          "reserved_mb": 0.0,
          "total_mb": 6143.9,
          "free_mb": 4673.0,
          "note": ""
        }
      ]
    },
    {
      "name": "coexistence",
      "started_at": "2026-05-03T11:56:28.162645",
      "finished_at": "2026-05-03T11:56:32.244213",
      "status": "error",
      "metadata": {
        "clap": "laion/larger_clap_music",
        "siglip2": "google/siglip2-base-patch16-384",
        "siglip2_load": "TypeError: expected str, bytes or os.PathLike object, not NoneType",
        "coexistence_possible": false,
        "siglip2_oom": false
      },
      "error": "Coexistenz-Test fehlgeschlagen, kein OOM",
      "snapshots": [
        {
          "label": "coex_before_anything",
          "timestamp": "2026-05-03T11:56:28.162645",
          "allocated_mb": 0.0,
          "reserved_mb": 0.0,
          "total_mb": 6143.9,
          "free_mb": 4673.0,
          "note": ""
        },
        {
          "label": "coex_after_clap_loaded",
          "timestamp": "2026-05-03T11:56:31.469189",
          "allocated_mb": 742.0,
          "reserved_mb": 776.0,
          "total_mb": 6143.9,
          "free_mb": 3897.0,
          "note": ""
        },
        {
          "label": "coex_siglip2_load_failed",
          "timestamp": "2026-05-03T11:56:32.119813",
          "allocated_mb": 742.0,
          "reserved_mb": 776.0,
          "total_mb": 6143.9,
          "free_mb": 3897.0,
          "note": ""
        },
        {
          "label": "coex_after_cleanup",
          "timestamp": "2026-05-03T11:56:32.244213",
          "allocated_mb": 0.0,
          "reserved_mb": 0.0,
          "total_mb": 6143.9,
          "free_mb": 4673.0,
          "note": ""
        }
      ]
    }
  ]
}