{
  "generated_at": "2026-05-06T09:23:16.310878",
  "environment": {
    "python": "3.10.20",
    "torch": "1.12.1+cu113",
    "cuda_available": "True",
    "device_name": "NVIDIA GeForce GTX 1060",
    "transformers": "4.38.2"
  },
  "results": [
    {
      "name": "clap_embedder",
      "status": "ok",
      "duration_s": 0.2787039279937744,
      "detail": {
        "n_files": 1,
        "model": "laion/larger_clap_music",
        "files_processed": 1,
        "per_file_times_s": [
          0.03877401351928711
        ],
        "avg_per_file_s": 0.03877401351928711,
        "extrapolated_500_clips_minutes": 0.3231167793273926,
        "cache_hits_first_pass": 1,
        "cache_misses_first_pass": 0,
        "re_import_hits": 1,
        "re_import_total_s": 0.013763904571533203,
        "re_import_hit_rate": 1.0,
        "knn_self_match_distance": null
      },
      "error": ""
    },
    {
      "name": "siglip_embedder",
      "status": "ok",
      "duration_s": 0.14881563186645508,
      "detail": {
        "n_files": 1,
        "model": "google/siglip2-base-patch16-384",
        "files_processed": 1,
        "per_file_times_s": [
          0.030190706253051758
        ],
        "avg_per_file_s": 0.030190706253051758,
        "extrapolated_500_clips_minutes": 0.25158921877543133,
        "re_import_hits": 1,
        "re_import_total_s": 0.00717473030090332,
        "re_import_hit_rate": 1.0,
        "knn_self_match_distance": null
      },
      "error": ""
    }
  ]
}